myquerybuilder
