Metadata-Version: 1.1
Name: MysqlSimpleQueryBuilder
Version: 0.3.2
Summary: Simple MySQL query builder and profiler
Home-page: https://bitbucket.org/saaj/mysql-simple-query-builder
Author: saaj
Author-email: mail@saaj.me
License: LGPL-2.1+
Keywords: python mysql
Platform: Any
Classifier: Topic :: Database
Classifier: Topic :: Software Development :: Libraries
Classifier: Programming Language :: Python :: 2.7
Classifier: Programming Language :: Python :: 3.3
Classifier: Programming Language :: Python :: 3.4
Classifier: Programming Language :: Python :: Implementation :: CPython
Classifier: Programming Language :: Python :: Implementation :: PyPy
Classifier: Intended Audience :: Developers
